chrisbase/__init__.py
chrisbase/cli.py
chrisbase/data.py
chrisbase/io.py
chrisbase/net.py
chrisbase/time.py
chrisbase/util.py
chrisbase-0.6.0.post2.dist-info/licenses/LICENSE
chrisbase-0.6.0.post2.dist-info/METADATA
chrisbase-0.6.0.post2.dist-info/WHEEL
chrisbase-0.6.0.post2.dist-info/entry_points.txt
chrisbase-0.6.0.post2.dist-info/top_level.txt
chrisbase-0.6.0.post2.dist-info/zip-safe
chrisbase-0.6.0.post2.dist-info/RECORD
